pipeline/__init__.py
pipeline/extractor.py
pipeline/loader.py
pipeline/main.py
pipeline/transformer.py
python_etl_pipeline-0.0.2.dist-info/METADATA
python_etl_pipeline-0.0.2.dist-info/WHEEL
python_etl_pipeline-0.0.2.dist-info/top_level.txt
python_etl_pipeline-0.0.2.dist-info/RECORD
